CodeforcesAPI/APIRequest.py
CodeforcesAPI/Blogs.py
CodeforcesAPI/Codeforces.py
CodeforcesAPI/Contests.py
CodeforcesAPI/Exceptions.py
CodeforcesAPI/Users.py
CodeforcesAPI/__init__.py
CodeforcesAPI/version.py
CodeforcesAPI-0.0.1.dist-info/LICENSE
CodeforcesAPI-0.0.1.dist-info/METADATA
CodeforcesAPI-0.0.1.dist-info/WHEEL
CodeforcesAPI-0.0.1.dist-info/top_level.txt
CodeforcesAPI-0.0.1.dist-info/RECORD
